alu_latch.v
module alu_latch(
    input clock,               // System clock
    input reset,               // System reset
    input store_high,          // Load top 8 bits on data bus
    input store_low,           // Load low 8 bits on data bus
    input grab,                // Latch ALU result 
    input [15:0] alu_result,   // ALU result from ALU module
    input [2:0] flags_in,      // Flags result from ALU module
    output reg [7:0] data_out, // 8 bits data loaded into data bus
    output reg [2:0] flags_out  // 3 bits flag result
);
    
reg [15:0] alu_value;

always @(posedge clock) begin
    if (reset == 1'b0) begin
        alu_value <= 16'd0;      // Use non-blocking assignment
        flags_out <= 3'd0;
    end
    else if (grab == 1'b1) begin // Latch ALU result when grab signal is high
        alu_value <= alu_result;  
        flags_out <= flags_in;    
    end
end

always @* begin
    if (store_high == 1'b1) begin // Load top 8 bits of ALU result on data bus
        data_out = alu_value[15:8];
    end
    else if (store_low == 1'b1) begin // Load low 8 bits of ALU result on data bus
        data_out = alu_value[7:0];
    end
    else begin
        data_out = 8'hzz; // Maintain high impedance on data bus
    end
end

endmodule

alu_latch_tb.v
`timescale 1 ns / 10 ps

module alu_latch_tb();
    reg clock = 1'b0;                // System clock
    reg reset = 1'b1;                // System reset
    reg store_high;                  // Load top 8 bits on data bus
    reg store_low;                   // Load low 8 bits on data bus
    reg grab;                        // Latch ALU result 
    reg [15:0] alu_result;           // ALU result from ALU module
    reg [2:0] flags_in;              // Flags result from ALU module
    wire [7:0] data_out;             // 8 bits data loaded into data bus
    wire [2:0] flags_out;            // 3 bits flag result

    // Clock generation
    initial begin
        clock = 1'b0;
        forever #50 clock = ~clock; // 20 MHz clock
    end

    alu_latch alu_latch_dut(
        .clock(clock),
        .reset(reset),
        .store_high(store_high),
        .store_low(store_low),
        .grab(grab),
        .alu_result(alu_result),
        .flags_in(flags_in),
        .data_out(data_out),
        .flags_out(flags_out)
    );

    initial begin
        // Reset
        @(negedge clock) begin
            reset = 1'b0;
        end
        checkCount(8'hzz, 3'd0, `__LINE__);

        @(negedge clock) begin
            reset = 1'b1;
        end
        checkCount(8'hzz, 3'd0, `__LINE__);

        @(negedge clock) begin
            grab = 1'b1;                  // ALU result should be grabbed and stored in internal register
            alu_result = 16'hfeef;
            flags_in = 3'b101;
        end
        checkCount(8'hzz, 3'b101, `__LINE__);

        @(negedge clock) begin
            grab = 1'b0;
            alu_result = 16'heffe;
            flags_in = 3'b111;
        end
        checkCount(8'hzz, 3'b101, `__LINE__);

        @(negedge clock) begin
            store_high = 1'b1;           // data_out should have high 8 bits of internal register
        end
        checkCount(8'hfe, 3'b101, `__LINE__);
        
        @(negedge clock) begin
            store_high = 1'b0;
        end
        checkCount(8'hzz, 3'b101, `__LINE__);

        @(negedge clock) begin
            store_low = 1'b1;            // data_out should have low 8 bits of internal register
        end
        checkCount(8'hef, 3'b101, `__LINE__);

        @(negedge clock) begin
            store_low = 1'b0;
        end
        checkCount(8'hzz, 3'b101, `__LINE__);
        
        @(negedge clock) begin            // As store_high has higher precedence, data_out should have high 8 bits of internal register 
            store_high = 1'b1;
            store_low = 1'b1;
        end
        checkCount(8'hfe, 3'b101, `__LINE__);

        $finish;
    end

    // Waveform log file and monitoring
    initial begin
        $dumpfile("alu_latch.vcd");
        $dumpvars(0);
        //$monitor("time: %d, data out: %d, flags out: %d ", $time, data_out, flags_out);
    end

    task checkCount(input [7:0] data_expected, input [2:0] flags_expected, input integer lineNum);
    begin
        @(posedge clock) #5 begin
            if (data_out === data_expected) begin
                $display("%3d - Test passed! for Data Out", lineNum);
            end
            else begin
                $display("%3d - Test failed! for Data Out, expected %h, got %h", lineNum, data_expected, data_out);
            end
            if (flags_out == flags_expected) begin
                $display("%3d - Test passed! for Flags Out", lineNum);
            end
            else begin
                $display("%3d - Test failed! for Flags Out, expected %b, got %b", lineNum, flags_expected, flags_out);
            end
        end
    end
    endtask

endmodule

alu_latch.vcd
$date
	Sun Nov 03 15:12:35 2024
$end
$version
	Icarus Verilog
$end
$timescale
	10ps
$end
$scope module alu_latch_tb $end
$var wire 3 ! flags_out [2:0] $end
$var wire 8 " data_out [7:0] $end
$var reg 16 # alu_result [15:0] $end
$var reg 1 $ clock $end
$var reg 3 % flags_in [2:0] $end
$var reg 1 & grab $end
$var reg 1 ' reset $end
$var reg 1 ( store_high $end
$var reg 1 ) store_low $end
$scope module alu_latch_dut $end
$var wire 16 * alu_result [15:0] $end
$var wire 1 $ clock $end
$var wire 3 + flags_in [2:0] $end
$var wire 1 & grab $end
$var wire 1 ' reset $end
$var wire 1 ( store_high $end
$var wire 1 ) store_low $end
$var reg 16 , alu_value [15:0] $end
$var reg 8 - data_out [7:0] $end
$var reg 3 . flags_out [2:0] $end
$upscope $end
$scope task checkCount $end
$var reg 8 / data_expected [7:0] $end
$var reg 3 0 flags_expected [2:0] $end
$var integer 32 1 lineNum [31:0] $end
$upscope $end
$upscope $end
$enddefinitions $end
$comment Show the parameter values. $end
$dumpall
$end
#0
$dumpvars
bx 1
bx 0
bx /
bx .
bx -
bx ,
bx +
bx *
x)
x(
1'
x&
bx %
0$
bx #
bx "
bx !
$end
#5000
1$
#10000
b100101 1
b0 0
bz /
0'
0$
#15000
bz "
bz -
b0 !
b0 .
b0 ,
1$
#20000
b101010 1
1'
0$
#25000
1$
#30000
b110001 1
b101 0
b101 %
b101 +
b1111111011101111 #
b1111111011101111 *
1&
0$
#35000
b101 !
b101 .
b1111111011101111 ,
1$
#40000
b111000 1
b111 %
b111 +
b1110111111111110 #
b1110111111111110 *
0&
0$
#45000
1$
#50000
b11111110 "
b11111110 -
b111101 1
b11111110 /
1(
0$
#55000
1$
#60000
bz "
bz -
b1000010 1
bz /
0(
0$
#65000
1$
#70000
b11101111 "
b11101111 -
b1000111 1
b11101111 /
1)
0$
#75000
1$
#80000
bz "
bz -
b1001100 1
bz /
0)
0$
#85000
1$
#90000
b11111110 "
b11111110 -
b1010010 1
b11111110 /
1)
1(
0$
