program_counter.v
module program_counter(
    input clock,                // System clock
    input reset,                // Synchronous reset, Active Low
    input increment,            // Increments counter when high
    input jump_set,            // When jump_set is high, PC loads newcount from JUMP module
    input [15:0] jumpcount,    // New address of counter from JUMP module
    output reg [15:0] count     // Output address of counter
);

always @(posedge clock) begin
    if (~reset) begin           // When reset is low, count is set to zero
        count <= 0;
    end
    else if (jump_set) begin   // When jump_set is high, newcount is loaded into counter
        count <= jumpcount;
    end
    else if (increment) begin   // When increment is high, count is incremented by one
        count <= count + 1;
    end
end

endmodule

program_countertb.v
`timescale 1 ns / 10 ps

module program_counter_test();
    reg clock = 1'b0;               // system clock
    reg reset = 1'b1;               // Active low reset
    reg increment = 1'b0;           // set high from external source    
    reg jump_set = 1'b0;            // set high from external source
    reg [15:0] jumpcount = 16'hFFFE; // Input value to the counter
    wire [15:0] count;              // Counter output for accessing memory

    // Clock generation
    initial begin
        clock = 1'b0;
        forever #50 clock = ~clock; // 100 time ticks per cycle = 10 MHz clock
    end

    // Instantiate the program counter
    program_counter dut (
        .clock(clock), 
        .reset(reset), 
        .increment(increment), 
        .jump_set(jump_set), 
        .jumpcount(jumpcount), 
        .count(count)
    );

    // Test sequence
    initial begin
        // Test reset
        reset = 1'b0; // Assert reset
        #100;         // Wait for a while
        reset = 1'b1; // Deassert reset
        #100;         // Wait for a while
        
        // Test increment
        increment = 1'b1; // Enable increment
        #200;             // Wait for a while
        increment = 1'b0; // Disable increment

        // Test jump
        jump_set = 1'b1; // Enable jump
        #100;            // Wait for a while
        jump_set = 1'b0; // Disable jump

        // Finish the simulation
        #100;
        $finish;
    end
    initial begin
        $dumpfile("output.vcd");
        $dumpvars(0);
    end
endmodule

PC.vcd
$date
	Sun Nov 03 12:31:31 2024
$end
$version
	Icarus Verilog
$end
$timescale
	10ps
$end
$scope module program_counter_test $end
$var wire 16 ! count [15:0] $end
$var reg 1 " clock $end
$var reg 1 # increment $end
$var reg 1 $ jump_set $end
$var reg 16 % jumpcount [15:0] $end
$var reg 1 & reset $end
$scope module dut $end
$var wire 1 " clock $end
$var wire 1 # increment $end
$var wire 1 $ jump_set $end
$var wire 16 ' jumpcount [15:0] $end
$var wire 1 & reset $end
$var reg 16 ( count [15:0] $end
$upscope $end
$upscope $end
$enddefinitions $end
$comment Show the parameter values. $end
$dumpall
$end
#0
$dumpvars
bx (
b1111111111111110 '
0&
b1111111111111110 %
0$
0#
0"
bx !
$end
#5000
b0 !
b0 (
1"
#10000
0"
1&
#15000
1"
#20000
0"
1#
#25000
b1 !
b1 (
1"
#30000
0"
#35000
b10 !
b10 (
1"
#40000
0"
1$
0#
#45000
b1111111111111110 !
b1111111111111110 (
1"
#50000
0"
0$
