register_16bit.v
module register_16bit(
    input clock,
    input reset,
    input loadhigh,
    input loadlow,
    input [7:0] halfvaluein,
    output reg [15:0] valueout
);

always @(posedge clock) begin
    if (reset == 1'b0) begin
        valueout <= 16'b0;
    end
    else if (loadhigh == 1'b1) begin
        valueout[15:8] <= halfvaluein;
    end
    else if (loadlow == 1'b1) begin
        valueout[7:0] <= halfvaluein;
    end
end

endmodule

register_16bit_tb.v
`timescale 1 ns / 10 ps

module register_16bit_tb();
    reg clock = 1'b0;              // system clock
    reg reset = 1'b1;              // Reset Active Low
    reg loadhigh = 1'b0;           // set high from external source
    reg loadlow = 1'b0;            // set high from external source
    reg [7:0] halfvaluein = 8'hFF; // 8-bit input to register
    wire [15:0] valueout;          // 16-bit output of 16-bit register

    register_16bit dut (
        .clock(clock),
        .reset(reset),
        .loadhigh(loadhigh),
        .loadlow(loadlow),
        .halfvaluein(halfvaluein),
        .valueout(valueout)
    );

    // Clock generation
    initial begin
        clock = 1'b0;
        forever #50 clock = ~clock; // 20 MHz clock
    end

    initial begin
        // Reset
        @(negedge clock) begin
            reset = 1'b0;
        end
        checkCount(16'b0, `__LINE__);

        // Setting reset back to high    
        @(negedge clock) begin
            reset = 1'b1;
        end
        checkCount(16'b0, `__LINE__);

        // Load High set to 1
        @(negedge clock) begin
            loadhigh = 1'b1;
        end
        checkCount(16'hFF00, `__LINE__);

        // Load High set to 0
        @(negedge clock) begin
            loadhigh = 1'b0;
            halfvaluein = 8'hee; // Change halfvaluein to 8'hee
        end
        checkCount(16'hFF00, `__LINE__);

        // Load Low set to 1
        @(negedge clock) begin
            loadlow = 1'b1;
        end
        checkCount(16'hFFEE, `__LINE__);

        // Load Low set to 0
        @(negedge clock) begin
            loadlow = 1'b0;
            halfvaluein = 8'hee; // Change halfvaluein to 8'hee
        end
        checkCount(16'hFFEE, `__LINE__);

        // Both Load high & Load low are set; loadhigh should execute as per precedence
        @(negedge clock) begin
            loadhigh = 1'b1;
            loadlow = 1'b1;
        end
        checkCount(16'hEEEE, `__LINE__);

        // Stop simulation
        $finish;
    end

    // Waveform log file and monitoring
    initial begin
        $dumpfile("register_16bit.vcd");
        $dumpvars(0);
        $monitor("time: %d, value: %h", $time, valueout);
    end

    task checkCount(input [15:0] expected, input integer lineNum);
    begin
        @(posedge clock) #5 begin
            if (valueout === expected) begin
                $display("%3d - Test passed", lineNum);
            end
            else begin
                $display("%3d - Test failed, expected %h, got %h", lineNum, expected, valueout);
            end
        end
    end
    endtask

endmodule

register_16bit.vcd
$date
	Sun Nov 03 12:51:09 2024
$end
$version
	Icarus Verilog
$end
$timescale
	10ps
$end
$scope module register_16bit_tb $end
$var wire 16 ! valueout [15:0] $end
$var reg 1 " clock $end
$var reg 8 # halfvaluein [7:0] $end
$var reg 1 $ loadhigh $end
$var reg 1 % loadlow $end
$var reg 1 & reset $end
$scope module dut $end
$var wire 1 " clock $end
$var wire 8 ' halfvaluein [7:0] $end
$var wire 1 $ loadhigh $end
$var wire 1 % loadlow $end
$var wire 1 & reset $end
$var reg 16 ( valueout [15:0] $end
$upscope $end
$scope task checkCount $end
$var reg 16 ) expected [15:0] $end
$var integer 32 * lineNum [31:0] $end
$upscope $end
$upscope $end
$enddefinitions $end
$comment Show the parameter values. $end
$dumpall
$end
#0
$dumpvars
bx *
bx )
bx (
b11111111 '
1&
0%
0$
b11111111 #
0"
bx !
$end
#5000
1"
#10000
b11111 *
b0 )
0&
0"
#15000
b0 !
b0 (
1"
#20000
b100101 *
1&
0"
#25000
1"
#30000
b101011 *
b1111111100000000 )
1$
0"
#35000
b1111111100000000 !
b1111111100000000 (
1"
#40000
b110010 *
b11101110 #
b11101110 '
0$
0"
#45000
1"
#50000
b111000 *
b1111111111101110 )
1%
0"
#55000
b1111111111101110 !
b1111111111101110 (
1"
#60000
b111111 *
0%
0"
#65000
1"
#70000
b1000110 *
b1110111011101110 )
1%
1$
0"
#75000
b1110111011101110 !
b1110111011101110 (
1"
